__init__.py
sinapsis_chatbots_base/__init__.py
sinapsis_chatbots_base/helpers/__init__.py
sinapsis_chatbots_base/helpers/huggingface_access_keys.py
sinapsis_chatbots_base/helpers/llm_keys.py
sinapsis_chatbots_base/helpers/postprocess_text.py
sinapsis_chatbots_base/helpers/tags.py
sinapsis_chatbots_base/templates/__init__.py
sinapsis_chatbots_base/templates/llm_text_completion_base.py
sinapsis_chatbots_base/templates/query_contextualize.py
sinapsis_chatbots_base/templates/query_contextualize_from_file.py
sinapsis_chatbots_base-0.1.12.dist-info/licenses/LICENSE
sinapsis_chatbots_base-0.1.12.dist-info/METADATA
sinapsis_chatbots_base-0.1.12.dist-info/WHEEL
sinapsis_chatbots_base-0.1.12.dist-info/top_level.txt
sinapsis_chatbots_base-0.1.12.dist-info/RECORD
