Metadata-Version: 2.4
Name: sinapsis-chatbots-base
Version: 0.1.12
Summary: Sinapsis base templates for LLM text completion.
Author-email: SinapsisAI <dev@sinapsis.tech>
Project-URL: Homepage, https://sinapsis.tech
Project-URL: Documentation, https://docs.sinapsis.tech/docs
Project-URL: Tutorials, https://docs.sinapsis.tech/tutorials
Project-URL: Repository, https://github.com/Sinapsis-AI/sinapsis-chatbots.git
Requires-Python: >=3.10
License-File: LICENSE
Requires-Dist: sinapsis>=0.2.10
Requires-Dist: torch>=2.6.0
Provides-Extra: chatbot
Requires-Dist: sinapsis-data-readers[ffmpeg,opencv,pydub,soundfile]>=0.1.13; extra == "chatbot"
Requires-Dist: sinapsis-data-writers[opencv]>=0.1.15; extra == "chatbot"
Requires-Dist: sinapsis-generic-data-tools>=0.1.9; extra == "chatbot"
Requires-Dist: sinapsis-huggingface-transformers>=0.1.0; extra == "chatbot"
Requires-Dist: sinapsis-langchain-readers[langchain-pdfs-readers]>=0.1.4; extra == "chatbot"
Requires-Dist: sinapsis-langchain-readers[langchain-wikipedia-readers]>=0.1.4; extra == "chatbot"
Requires-Dist: sinapsis-langchain-readers[langchain-productivity-tools]>=0.1.4; extra == "chatbot"
Requires-Dist: sinapsis[webapp]>=0.2.19; extra == "chatbot"
Provides-Extra: all
Requires-Dist: sinapsis-chatbots-base[chatbot]; extra == "all"
Dynamic: license-file
